catscore/__init__.py
catscore/db/__init__.py
catscore/db/mysql.py
catscore/http/__init__.py
catscore/http/error.py
catscore/http/request.py
catscore/http/response.py
catscore/http/tor.py
catscore/http/web_driver.py
catscore/lib/__init__.py
catscore/lib/emoji.py
catscore/lib/env.py
catscore/lib/functional.py
catscore/lib/io.py
catscore/lib/logger.py
catscore/lib/pandas.py
catscore/lib/process.py
catscore/lib/time.py
tests/__init__.py
tests/http/__init__.py
tests/http/request.py
tests/http/test_web_driver.py
catscore-0.3.5.dist-info/METADATA
catscore-0.3.5.dist-info/WHEEL
catscore-0.3.5.dist-info/top_level.txt
catscore-0.3.5.dist-info/RECORD
