Metadata-Version: 2.1
Name: catscore
Version: 0.3.5
Summary: Core library for crawling and web scraping
Home-page: https://rescala.jp
Author: rv
Author-email: yo-maruya@rescala.jp
License: MIT
Project-URL: Bug Reports, https://github.com/rv-rescala/catscore/issues
Project-URL: Source, https://github.com/rv-rescala/catscore
Keywords: python crawler scraping
Platform: UNKNOWN
Requires-Python: >=3.7
Requires-Dist: requests
Requires-Dist: bs4
Requires-Dist: selenium
Requires-Dist: lxml
Requires-Dist: asgiref
Requires-Dist: aiohttp
Requires-Dist: emoji
Requires-Dist: pillow
Requires-Dist: slackweb
Requires-Dist: sqlalchemy
Requires-Dist: pysocks
